google_pygram.py
google_pygram-0.0.1.dist-info/LICENSE
google_pygram-0.0.1.dist-info/METADATA
google_pygram-0.0.1.dist-info/WHEEL
google_pygram-0.0.1.dist-info/top_level.txt
google_pygram-0.0.1.dist-info/RECORD
