Metadata-Version: 2.1
Name: google-pygram
Version: 0.0.1
Summary: API Interface for Google NGram
Author: Omar Ibrahim
Classifier: Programming Language :: Python :: 3
Classifier: License :: OSI Approved :: MIT License
Classifier: Operating System :: OS Independent
Requires-Python: >=3.6
License-File: LICENSE
Requires-Dist: requests
Requires-Dist: pandas
